[

  {
    "url": "https://api.github.com/repos/cfrg/draft-irtf-cfrg-hpke/issues/1",
    "repository_url": "https://api.github.com/repos/cfrg/draft-irtf-cfrg-hpke",
    "labels_url": "https://api.github.com/repos/cfrg/draft-irtf-cfrg-hpke/issues/1/labels{/name}",
    "comments_url": "https://api.github.com/repos/cfrg/draft-irtf-cfrg-hpke/issues/1/comments",
    "events_url": "https://api.github.com/repos/cfrg/draft-irtf-cfrg-hpke/issues/1/events",
    "html_url": "https://github.com/cfrg/draft-irtf-cfrg-hpke/pull/1",
    "id": 457214200,
    "node_id": "MDExOlB1bGxSZXF1ZXN0Mjg5MDcyNTg2",
    "number": 1,
    "title": "Comments from @dwd (and one thing I found)",
    "user": {
      "login": "bifurcation",
      "id": 75597,
      "node_id": "MDQ6VXNlcjc1NTk3",
      "avatar_url": "https://avatars0.githubusercontent.com/u/75597?v=4",
      "gravatar_id": "",
      "url": "https://api.github.com/users/bifurcation",
      "html_url": "https://github.com/bifurcation",
      "followers_url": "https://api.github.com/users/bifurcation/followers",
      "following_url": "https://api.github.com/users/bifurcation/following{/other_user}",
      "gists_url": "https://api.github.com/users/bifurcation/gists{/gist_id}",
      "starred_url": "https://api.github.com/users/bifurcation/starred{/owner}{/repo}",
      "subscriptions_url": "https://api.github.com/users/bifurcation/subscriptions",
      "organizations_url": "https://api.github.com/users/bifurcation/orgs",
      "repos_url": "https://api.github.com/users/bifurcation/repos",
      "events_url": "https://api.github.com/users/bifurcation/events{/privacy}",
      "received_events_url": "https://api.github.com/users/bifurcation/received_events",
      "type": "User",
      "site_admin": false
    },
    "labels": [

    ],
    "state": "open",
    "locked": false,
    "assignee": null,
    "assignees": [

    ],
    "milestone": null,
    "comments": 0,
    "created_at": "2019-06-18T01:17:07Z",
    "updated_at": "2019-07-01T17:57:35Z",
    "closed_at": null,
    "author_association": "COLLABORATOR",
    "pull_request": {
      "url": "https://api.github.com/repos/cfrg/draft-irtf-cfrg-hpke/pulls/1",
      "html_url": "https://github.com/cfrg/draft-irtf-cfrg-hpke/pull/1",
      "diff_url": "https://github.com/cfrg/draft-irtf-cfrg-hpke/pull/1.diff",
      "patch_url": "https://github.com/cfrg/draft-irtf-cfrg-hpke/pull/1.patch"
    },
    "body": ""
  }

]
